MountainProjectPublicAPI/MountainProjectPublicAPI.py
MountainProjectPublicAPI/__init__.py
MountainProjectPublicAPI-0.1.0.dist-info/METADATA
MountainProjectPublicAPI-0.1.0.dist-info/WHEEL
MountainProjectPublicAPI-0.1.0.dist-info/top_level.txt
MountainProjectPublicAPI-0.1.0.dist-info/RECORD
