Metadata-Version: 2.1
Name: MountainProjectPublicAPI
Version: 0.1.0
Summary: Python Wrapper for Mountain Project public data API
Home-page: https://github.com/jacktlange/MountainProject-Python-API
Author: Jack Lange
Author-email: jacktlange@gmail.com
License: UNKNOWN
Platform: UNKNOWN
Classifier: Programming Language :: Python :: 3
Classifier: License :: OSI Approved :: MIT License
Classifier: Operating System :: OS Independent
